gmap2baidu/__about__.py
gmap2baidu/__init__.py
gmap2baidu/gmap2baidu.py
gmap2baidu/urls.py
gmap2baidu-0.0.2.dist-info/METADATA
gmap2baidu-0.0.2.dist-info/WHEEL
gmap2baidu-0.0.2.dist-info/entry_points.txt
gmap2baidu-0.0.2.dist-info/licenses/LICENSE
gmap2baidu-0.0.2.dist-info/RECORD
