Metadata-Version: 2.3
Name: gmap2baidu
Version: 0.0.2
Summary: Wrapper for prcoords library to convert Google / Bing Maps / Sat imagery coordinates in decimal degrees (WGS-84 or GCJ-02) to Baidu Map (BD-09) or other chinese maps.
Project-URL: Homepage, https://github.com/balestek/gmap2baidu
Project-URL: Bug Tracker, https://github.com/balestek/gmap2baidu/issues
Author: balestek
License:                     GNU GENERAL PUBLIC LICENSE
License-File: LICENSE
Keywords: GCJ-02,amap,amap.com,baidu,baidu-map,baidumap,bd-09,bd09,gcj02,google,google-maps,googlemaps,pipx,prcoords,pypi,python,qq-map,qqmap,wsg-84,wsg84
Classifier: Development Status :: 4 - Beta
Classifier: Environment :: Console
Classifier: License :: OSI Approved :: GNU General Public License v3 (GPLv3)
Classifier: Natural Language :: English
Classifier: Operating System :: OS Independent
Classifier: Programming Language :: Python :: 3
Classifier: Programming Language :: Python :: 3.8
Classifier: Programming Language :: Python :: 3.9
Classifier: Programming Language :: Python :: 3.10
Classifier: Programming Language :: Python :: 3.11
Classifier: Programming Language :: Python :: 3.12
Requires-Python: >=3.8
Requires-Dist: colorama
Requires-Dist: prcoords
